{"config": {"view": {"continuousWidth": 400, "continuousHeight": 300}}, "data": {"name": "data-8c99a90ffe5b21bdd9cc4ba7ee5a30c2"}, "mark": {"type": "area", "color": "gray", "opacity": 0.2}, "encoding": {"tooltip": [{"aggregate": "count", "field": "score", "type": "quantitative"}], "x": {"field": "score", "type": "quantitative"}, "y": {"field": "density", "type": "quantitative"}}, "$schema": "https://vega.github.io/schema/vega-lite/v4.17.0.json", "datasets": {"data-8c99a90ffe5b21bdd9cc4ba7ee5a30c2": [{"score": 70, "density": 0.04429223334180998}, {"score": 84, "density": 0.0311342793208359}, {"score": 73, "density": 0.09033037923341058}, {"score": 99, "density": 0.47233810940761456}, {"score": 86, "density": 0.10000309247614658}]}}